README.md
setup.cfg
setup.py
gui_test/Binomialdistribution.py
gui_test/Gaussiandistribution.py
gui_test/Generaldistribution.py
gui_test/__init__.py
gui_test.egg-info/PKG-INFO
gui_test.egg-info/SOURCES.txt
gui_test.egg-info/dependency_links.txt
gui_test.egg-info/not-zip-safe
gui_test.egg-info/top_level.txt